Assignment.py
Module.py
ulpsych_assistant-0.0.0.1.dist-info/METADATA
ulpsych_assistant-0.0.0.1.dist-info/WHEEL
ulpsych_assistant-0.0.0.1.dist-info/top_level.txt
ulpsych_assistant-0.0.0.1.dist-info/RECORD
