Metadata-Version: 2.1
Name: ulpsych-assistant
Version: 0.0.0.1
Summary: A tool for helping people with administration tasks, with a focus on grading admin and module setup
Home-page: UNKNOWN
Author: Kevin O'Malley
Author-email: kevin.omalley@ul.ie
License: GNU GPL
Platform: UNKNOWN
Classifier: Development Status :: 3 - Alpha
Classifier: Topic :: Utilities
